qprop/__init__.py
qprop/core.py
qprop/version.py
qprop-0.0.2.dist-info/DESCRIPTION.rst
qprop-0.0.2.dist-info/METADATA
qprop-0.0.2.dist-info/RECORD
qprop-0.0.2.dist-info/WHEEL
qprop-0.0.2.dist-info/metadata.json
qprop-0.0.2.dist-info/top_level.txt
