Metadata-Version: 2.0
Name: qprop
Version: 0.0.2
Summary: Visualized QPROP
Home-page: UNKNOWN
Author: sahn
Author-email: jam31118@gmail.com
License: GPLv3
Keywords: visualization,physics,animation,plot,tdse,schrodinger equation
Platform: UNKNOWN
Classifier: Topic :: Scientific/Engineering :: Visualization
Classifier: License :: OSI Approved :: GNU Affero General Public License v3
Classifier: Programming Language :: Python :: 3.5
Classifier: Programming Language :: Python :: 3.6
Requires-Dist: numpy
Requires-Dist: matplotlib
Requires-Dist: pandas
Requires-Dist: vis
Requires-Dist: nunit
